api/app/config.py
api/app/main.py
api/app/schemas.py
api/app/vision.py
api/app/routes/classification.py
api/tests/conftest.py
api/tests/routes/test_classification.py
pyrovision/__init__.py
pyrovision/version.py
pyrovision/datasets/__init__.py
pyrovision/datasets/openfire.py
pyrovision/datasets/utils.py
pyrovision/models/__init__.py
pyrovision/models/mobilenetv3.py
pyrovision/models/resnet.py
pyrovision/models/rexnet.py
pyrovision/models/utils.py
references/clean_checkpoint.py
references/classification/train.py
pyrovision-0.2.0.dist-info/LICENSE
pyrovision-0.2.0.dist-info/METADATA
pyrovision-0.2.0.dist-info/WHEEL
pyrovision-0.2.0.dist-info/top_level.txt
pyrovision-0.2.0.dist-info/zip-safe
pyrovision-0.2.0.dist-info/RECORD
