Metadata-Version: 2.1
Name: pyrovision
Version: 0.2.0
Summary: Datasets and models for wildfire detection in PyTorch
Author-email: Pyronear <contact@pyronear.org>
License: Apache License
Project-URL: documentation, https://pyronear.org/pyro-vision
Project-URL: repository, https://github.com/pyronear/pyro-vision
Project-URL: tracker, https://github.com/pyronear/pyro-vision/issues
Keywords: pytorch,deep learning,vision,cnn,wildfire
Platform: UNKNOWN
Classifier: Development Status :: 4 - Beta
Classifier: Intended Audience :: Developers
Classifier: Intended Audience :: Science/Research
Classifier: License :: OSI Approved :: Apache Software License
Classifier: Natural Language :: English
Classifier: Operating System :: OS Independent
Classifier: Programming Language :: Python :: 3
Classifier: Programming Language :: Python :: 3.6
Classifier: Programming Language :: Python :: 3.7
Classifier: Programming Language :: Python :: 3.8
Classifier: Programming Language :: Python :: 3.9
Classifier: Topic :: Scientific/Engineering
Classifier: Topic :: Scientific/Engineering :: Mathematics
Classifier: Topic :: Scientific/Engineering :: Artificial Intelligence
Requires-Python: <4,>=3.6
License-File: LICENSE
Requires-Dist: torch (<2.0.0,>=1.11.0)
Requires-Dist: torchvision (<1.0.0,>=0.12.0)
Requires-Dist: tqdm (>=4.1.0)
Requires-Dist: requests (<3.0.0,>=2.20.0)
Requires-Dist: pylocron (<1.0.0,>=0.2.1)
Requires-Dist: huggingface-hub (>=0.4.0)
Provides-Extra: dev
Requires-Dist: pytest (>=5.3.2) ; extra == 'dev'
Requires-Dist: coverage[toml] (>=4.5.4) ; extra == 'dev'
Requires-Dist: requests (>=2.20.0) ; extra == 'dev'
Requires-Dist: torchvision (>=0.4.0) ; extra == 'dev'
Requires-Dist: flake8 (>=3.9.0) ; extra == 'dev'
Requires-Dist: isort (>=5.7.0) ; extra == 'dev'
Requires-Dist: mypy (>=0.812) ; extra == 'dev'
Requires-Dist: pydocstyle[toml] (>=6.0.0) ; extra == 'dev'
Requires-Dist: black (<23.0,>=22.1) ; extra == 'dev'
Requires-Dist: sphinx (!=3.5.0,>=3.0.0) ; extra == 'dev'
Requires-Dist: furo (>=2022.3.4) ; extra == 'dev'
Requires-Dist: sphinxemoji (>=0.1.8) ; extra == 'dev'
Requires-Dist: sphinx-copybutton (>=0.3.1) ; extra == 'dev'
Requires-Dist: Jinja2 (<3.1) ; extra == 'dev'
Provides-Extra: docs
Requires-Dist: sphinx (!=3.5.0,>=3.0.0) ; extra == 'docs'
Requires-Dist: furo (>=2022.3.4) ; extra == 'docs'
Requires-Dist: sphinxemoji (>=0.1.8) ; extra == 'docs'
Requires-Dist: sphinx-copybutton (>=0.3.1) ; extra == 'docs'
Requires-Dist: Jinja2 (<3.1) ; extra == 'docs'
Provides-Extra: quality
Requires-Dist: flake8 (>=3.9.0) ; extra == 'quality'
Requires-Dist: isort (>=5.7.0) ; extra == 'quality'
Requires-Dist: mypy (>=0.812) ; extra == 'quality'
Requires-Dist: pydocstyle[toml] (>=6.0.0) ; extra == 'quality'
Requires-Dist: black (<23.0,>=22.1) ; extra == 'quality'
Provides-Extra: test
Requires-Dist: pytest (>=5.3.2) ; extra == 'test'
Requires-Dist: coverage[toml] (>=4.5.4) ; extra == 'test'
Provides-Extra: training
Requires-Dist: wandb (<1.0.0,>=0.10.31) ; extra == 'training'
Requires-Dist: codecarbon (<3.0.0,>=2.0.0) ; extra == 'training'
